tribal_temp-0.0.1.dist-info/RECORD
tribal_temp-0.0.1.dist-info/LICENSE
tribal_temp-0.0.1.dist-info/WHEEL
tribal_temp-0.0.1.dist-info/top_level.txt
tribal_temp-0.0.1.dist-info/METADATA
tribal/__init__.py
tribal/misc/drawing.py
tribal/misc/__init__.py
tribal/algorithms/__init__.py
tribal/algorithms/algorithm_input.py
tribal/algorithms/src/__init__.py
tribal/algorithms/src/gmknn/__init__.py
tribal/algorithms/src/gmknn/source/gmknn_bfs.pyx
tribal/algorithms/src/gmknn/source/mknn.cpp
tribal/algorithms/src/gmknn/source/__init__.py
tribal/algorithms/src/gmknn/source/gmknn_lp.pyx
tribal/algorithms/src/gmknn/source/gmknn_connect.pyx
tribal/algorithms/src/gmknn/source/gmknn_lp.cpp
tribal/algorithms/src/gmknn/source/gmknn_connect.cpp
tribal/algorithms/src/gmknn/source/mknn.pyx
tribal/algorithms/src/gmknn/source/gmknn_bfs.cpp
tribal/algorithms/src/gmknn/binaries/mknn.cpython-311-darwin.so
tribal/algorithms/src/gmknn/binaries/gmknn_bfs.cpython-311-darwin.so
tribal/algorithms/src/gmknn/binaries/gmknn_bfs.cp311-win_amd64.pyd
tribal/algorithms/src/gmknn/binaries/mknn.cp311-win_amd64.pyd
tribal/algorithms/src/gmknn/binaries/gmknn_connect.cpython-311-darwin.so
tribal/algorithms/src/gmknn/binaries/__init__.py
tribal/algorithms/src/gmknn/binaries/gmknn_lp.cp311-win_amd64.pyd
tribal/algorithms/src/gmknn/binaries/gmknn_connect.cp311-win_amd64.pyd
tribal/algorithms/src/gmknn/binaries/gmknn_lp.cp310-win_amd64.pyd
tribal/algorithms/src/gmknn/binaries/gmknn_connect.cp310-win_amd64.pyd
tribal/algorithms/src/gmknn/binaries/mknn.cp310-win_amd64.pyd
tribal/algorithms/src/gmknn/binaries/gmknn_bfs.cp310-win_amd64.pyd
tribal/algorithms/src/gmknn/binaries/gmknn_lp.cpython-311-darwin.so
tribal/algorithms/src/genieclust/genieclustering_mst.cpython-311-darwin.so
tribal/algorithms/src/genieclust/__init__.py
tribal/algorithms/src/genieclust/genieclustering_mst.pyx
tribal/algorithms/src/genieclust/genieclustering_mst.cpp
tribal/algorithms/src/genieclust/c_mst.pxd
tribal/algorithms/src/genieclust/genieclustering_mst.cp311-win_amd64.pyd
tribal/algorithms/src/genieclust/c_argfuns.pxd
tribal/algorithms/src/mstl/__init__.py
